integration_tests/__init__.py
integration_tests/dynamodb_repository_integration_test.py
pygglz/__init__.py
pygglz/context_locator.py
pygglz/feature_context.py
pygglz/feature_snapshot.py
pygglz/feature_state.py
pygglz/features.py
pygglz/state_repository.py
pygglz/dynamodb/__init__.py
pygglz/dynamodb/dynamodb_repository.py
pygglz/file/__init__.py
pygglz/file/file_repository.py
pygglz/http/__init__.py
pygglz/http/http_repository.py
pygglz/memory/__init__.py
pygglz/memory/memory_repository.py
tests/__init__.py
tests/feature_context_test.py
tests/feature_snapshot_test.py
tests/feature_state_test.py
tests/features_with_in_memory_repository_test.py
tests/state_repository_test.py
tests/dynamodb/__init__.py
tests/dynamodb/dynamodb_repository_test.py
tests/file/__init__.py
tests/file/features_with_file_repository_test.py
tests/file/file_repository_test.py
tests/http/__init__.py
tests/http/http_repository_test.py
tests/memory/__init__.py
tests/memory/memory_repository_test.py
pygglz-0.0.7.dist-info/METADATA
pygglz-0.0.7.dist-info/WHEEL
pygglz-0.0.7.dist-info/top_level.txt
pygglz-0.0.7.dist-info/RECORD
