Metadata-Version: 2.1
Name: pygglz
Version: 0.0.7
Summary: A feature toggle library designed after Java togglz
Home-page: https://github.com/pygglz/pygglz
Author: Cornelius Buschka
Author-email: cbuschka@gmail.com
License: UNKNOWN
Platform: UNKNOWN
Classifier: Programming Language :: Python :: 3
Classifier: License :: OSI Approved :: Apache Software License
Classifier: Operating System :: OS Independent
Requires-Python: >=3.6
